{
    "status": "active",
    "total_steps": 340417,
    "target_steps": 3000000,
    "meters": {
        "pressure": {
            "val": 11.3,
            "color": "#da3633"
        },
        "maturity": {
            "val": 38,
            "color": "#d29922"
        }
    },
    "diagnosis": {
        "status_text": "生存の兆しあり (黄)",
        "status_color": "#d29922",
        "status_detail": "直近100戦: 56勝 (56%)"
    },
    "combat_stats": {
        "WIN": 5836,
        "FAIL": 62,
        "BUST": 3491
    },
    "ai_status": "Training (340,417)",
    "total_eps": 9389,
    "config": {
        "zones": [
            {
                "range": "0 - 33",
                "color": "#da3633",
                "title": "Zone 1: Awakening (赤)",
                "desc": "初期段階。勝率30%未満、または学習序盤。"
            },
            {
                "range": "33 - 66",
                "color": "#d29922",
                "title": "Zone 2: Hunting (橙)",
                "desc": "成長段階。勝率30-60%、または学習中盤。"
            },
            {
                "range": "66 - 99",
                "color": "#238636",
                "title": "Zone 3: Apex Predator (緑)",
                "desc": "完成段階。勝率60%以上、または学習終盤。"
            },
            {
                "range": "100",
                "color": "#dbab09",
                "title": "Zone 4: FANTASTIC BEAST (金)",
                "desc": "神の領域。勝率80%以上かつ完走。レインボー発動。"
            }
        ]
    },
    "analysis_report": {
        "overall_win_rate": "62.16 %",
        "overall_bust_rate": "37.18 %",
        "speed_stats": {
            "fastest": 2,
            "slowest": 288,
            "avg": 32.8
        },
        "margin_stats": {
            "lowest": 50.0,
            "highest": 999.0,
            "avg": 653.7
        },
        "distributions": {
            "speed": {
                "0-5m": 327,
                "5-30m": 3702,
                "30-60m": 1125,
                "60-120m": 453,
                "120m+": 229
            },
            "margin": {
                "50-60%": 12,
                "60-70%": 14,
                "70-80%": 16,
                "80-90%": 18,
                "90-100%": 17,
                "100%+": 5759
            }
        },
        "total_wins": 5836
    },
    "logs": [
        {
            "t": 14,
            "r": 9978.7,
            "l": 22,
            "beh": "WIN"
        },
        {
            "t": 13,
            "r": 9955.8,
            "l": 39,
            "beh": "WIN"
        },
        {
            "t": 12,
            "r": 5718.0,
            "l": 53,
            "beh": "WIN"
        },
        {
            "t": 11,
            "r": 10046.5,
            "l": 10,
            "beh": "WIN"
        },
        {
            "t": 10,
            "r": 9972.7,
            "l": 9,
            "beh": "WIN"
        },
        {
            "t": 9,
            "r": 9870.4,
            "l": 22,
            "beh": "WIN"
        },
        {
            "t": 8,
            "r": 8366.0,
            "l": 32,
            "beh": "WIN"
        },
        {
            "t": 7,
            "r": 9972.3,
            "l": 7,
            "beh": "WIN"
        },
        {
            "t": 6,
            "r": 9970.8,
            "l": 21,
            "beh": "WIN"
        },
        {
            "t": 5,
            "r": 10016.8,
            "l": 38,
            "beh": "WIN"
        },
        {
            "t": 4,
            "r": 9988.8,
            "l": 45,
            "beh": "WIN"
        },
        {
            "t": 3,
            "r": -17194.9,
            "l": 17,
            "beh": "DEATH"
        },
        {
            "t": 2,
            "r": 9998.8,
            "l": 115,
            "beh": "WIN"
        },
        {
            "t": 1,
            "r": -26286.6,
            "l": 95,
            "beh": "DEATH"
        },
        {
            "t": 0,
            "r": -14472.1,
            "l": 15,
            "beh": "DEATH"
        }
    ]
}