{
    "status": "active",
    "total_steps": 1472512,
    "target_steps": 2000000,
    "prog_pct": 73.6,
    "diagnosis": {
        "expected_phase": "Phase 4: 覇道",
        "actual_phase": "Phase 3: 覚醒への分水嶺",
        "status_text": "やや遅れ (Lagging)",
        "status_color": "#FFFF00"
    },
    "ai_status": "Learning (1,472,512 / 2,000,000)",
    "total_eps": 100,
    "avg_score": -6.7,
    "surv_rate": 57.0,
    "bust_rate": 32.0,
    "config": {
        "phases": [
            {
                "id": 1,
                "limit_ratio": 0.2,
                "color": "#FF4B4B",
                "min_score": -9999,
                "title": "Phase 1: 阿鼻叫喚の特攻",
                "desc": "資金管理を学習中（暴走・即死）"
            },
            {
                "id": 2,
                "limit_ratio": 0.5,
                "color": "#FFA500",
                "min_score": -500,
                "title": "Phase 2: 血塗れの学習",
                "desc": "生存時間の延長・逃げ腰"
            },
            {
                "id": 3,
                "limit_ratio": 0.7,
                "color": "#FFFF00",
                "min_score": -100,
                "title": "Phase 3: 覚醒への分水嶺",
                "desc": "損小利大の萌芽・生存確立"
            },
            {
                "id": 4,
                "limit_ratio": 0.9,
                "color": "#00FF00",
                "min_score": 100,
                "title": "Phase 4: 覇道",
                "desc": "トレンドフォロー・利益追求"
            },
            {
                "id": 5,
                "limit_ratio": 1.01,
                "color": "#0088FF",
                "min_score": 500,
                "title": "Phase 5: 市場支配",
                "desc": "完成されたロジック"
            }
        ]
    },
    "chart_json": {
        "$schema": "https://vega.github.io/schema/vega-lite/v5.json",
        "data": {
            "values": [
                {
                    "Type": "即死・破綻",
                    "Count": 32,
                    "Color": "#FF4B4B"
                },
                {
                    "Type": "損切り・敗北",
                    "Count": 27,
                    "Color": "#FFA500"
                },
                {
                    "Type": "辛勝・微益",
                    "Count": 17,
                    "Color": "#FFFF00"
                },
                {
                    "Type": "大勝利",
                    "Count": 24,
                    "Color": "#00FF00"
                }
            ]
        },
        "layer": [
            {
                "mark": "bar",
                "encoding": {
                    "x": {
                        "field": "Count",
                        "type": "quantitative",
                        "axis": {
                            "labelColor": "#ddd"
                        }
                    },
                    "y": {
                        "field": "Type",
                        "type": "nominal",
                        "sort": [
                            "大勝利",
                            "辛勝・微益",
                            "損切り・敗北",
                            "即死・破綻"
                        ],
                        "axis": {
                            "labelColor": "#ddd"
                        }
                    },
                    "color": {
                        "field": "Color",
                        "scale": null
                    }
                }
            },
            {
                "mark": {
                    "type": "text",
                    "align": "left",
                    "dx": 5,
                    "fill": "white"
                },
                "encoding": {
                    "x": {
                        "field": "Count",
                        "type": "quantitative"
                    },
                    "y": {
                        "field": "Type",
                        "type": "nominal"
                    },
                    "text": {
                        "field": "Count",
                        "type": "quantitative"
                    }
                }
            }
        ],
        "background": "transparent"
    },
    "line_json": {
        "$schema": "https://vega.github.io/schema/vega-lite/v5.json",
        "data": {
            "values": [
                {
                    "index": 0,
                    "r": -103.583691
                },
                {
                    "index": 1,
                    "r": 1013.3515
                },
                {
                    "index": 2,
                    "r": 1029.6685
                },
                {
                    "index": 3,
                    "r": -1004.283341
                },
                {
                    "index": 4,
                    "r": 207.931703
                },
                {
                    "index": 5,
                    "r": 97.539072
                },
                {
                    "index": 6,
                    "r": -95.328
                },
                {
                    "index": 7,
                    "r": 1016.84089
                },
                {
                    "index": 8,
                    "r": -1003.325332
                },
                {
                    "index": 9,
                    "r": -100.7935
                },
                {
                    "index": 10,
                    "r": 1011.516993
                },
                {
                    "index": 11,
                    "r": -107.917674
                },
                {
                    "index": 12,
                    "r": 1016.761094
                },
                {
                    "index": 13,
                    "r": -1001.651
                },
                {
                    "index": 14,
                    "r": 203.608
                },
                {
                    "index": 15,
                    "r": -1000.0
                },
                {
                    "index": 16,
                    "r": 202.26944
                },
                {
                    "index": 17,
                    "r": -300.0
                },
                {
                    "index": 18,
                    "r": -1000.0
                },
                {
                    "index": 19,
                    "r": 1032.374234
                },
                {
                    "index": 20,
                    "r": 1020.28018
                },
                {
                    "index": 21,
                    "r": -1002.821
                },
                {
                    "index": 22,
                    "r": 102.552611
                },
                {
                    "index": 23,
                    "r": 204.819997
                },
                {
                    "index": 24,
                    "r": -1000.0
                },
                {
                    "index": 25,
                    "r": 1013.38738
                },
                {
                    "index": 26,
                    "r": -1000.0
                },
                {
                    "index": 27,
                    "r": -101.972674
                },
                {
                    "index": 28,
                    "r": -300.0
                },
                {
                    "index": 29,
                    "r": -1000.0
                },
                {
                    "index": 30,
                    "r": -103.615574
                },
                {
                    "index": 31,
                    "r": -1001.759619
                },
                {
                    "index": 32,
                    "r": 98.9115
                },
                {
                    "index": 33,
                    "r": 1010.9665
                },
                {
                    "index": 34,
                    "r": -990.82
                },
                {
                    "index": 35,
                    "r": -1000.0
                },
                {
                    "index": 36,
                    "r": -106.987965
                },
                {
                    "index": 37,
                    "r": -1000.0
                },
                {
                    "index": 38,
                    "r": -1000.0
                },
                {
                    "index": 39,
                    "r": -1002.606105
                },
                {
                    "index": 40,
                    "r": -106.907807
                },
                {
                    "index": 41,
                    "r": -1000.0
                },
                {
                    "index": 42,
                    "r": -300.0
                },
                {
                    "index": 43,
                    "r": -103.733437
                },
                {
                    "index": 44,
                    "r": -1005.3515
                },
                {
                    "index": 45,
                    "r": 1049.410958
                },
                {
                    "index": 46,
                    "r": -1001.6255
                },
                {
                    "index": 47,
                    "r": -101.161634
                },
                {
                    "index": 48,
                    "r": -103.595016
                },
                {
                    "index": 49,
                    "r": 97.732384
                },
                {
                    "index": 50,
                    "r": -996.7735
                },
                {
                    "index": 51,
                    "r": -106.324
                },
                {
                    "index": 52,
                    "r": -1005.496077
                },
                {
                    "index": 53,
                    "r": -104.286029
                },
                {
                    "index": 54,
                    "r": -998.119
                },
                {
                    "index": 55,
                    "r": -1001.9975
                },
                {
                    "index": 56,
                    "r": -999.934784
                },
                {
                    "index": 57,
                    "r": 1013.9455
                },
                {
                    "index": 58,
                    "r": 1016.531158
                },
                {
                    "index": 59,
                    "r": 208.486448
                },
                {
                    "index": 60,
                    "r": -109.1855
                },
                {
                    "index": 61,
                    "r": 202.1905
                },
                {
                    "index": 62,
                    "r": 1010.0473
                },
                {
                    "index": 63,
                    "r": 101.818739
                },
                {
                    "index": 64,
                    "r": 1013.5675
                },
                {
                    "index": 65,
                    "r": -1000.0
                },
                {
                    "index": 66,
                    "r": -994.340282
                },
                {
                    "index": 67,
                    "r": -1000.995359
                },
                {
                    "index": 68,
                    "r": -109.156084
                },
                {
                    "index": 69,
                    "r": 1020.70397
                },
                {
                    "index": 70,
                    "r": 97.923152
                },
                {
                    "index": 71,
                    "r": 102.698666
                },
                {
                    "index": 72,
                    "r": -300.0
                },
                {
                    "index": 73,
                    "r": 1010.773
                },
                {
                    "index": 74,
                    "r": -1000.0
                },
                {
                    "index": 75,
                    "r": 95.5383
                },
                {
                    "index": 76,
                    "r": -208.874748
                },
                {
                    "index": 77,
                    "r": -1004.96
                },
                {
                    "index": 78,
                    "r": -103.82629
                },
                {
                    "index": 79,
                    "r": 204.967836
                },
                {
                    "index": 80,
                    "r": -300.0
                },
                {
                    "index": 81,
                    "r": 1011.049868
                },
                {
                    "index": 82,
                    "r": 103.750215
                },
                {
                    "index": 83,
                    "r": 1011.4795
                },
                {
                    "index": 84,
                    "r": -999.31348
                },
                {
                    "index": 85,
                    "r": 1012.314518
                },
                {
                    "index": 86,
                    "r": -106.0265
                },
                {
                    "index": 87,
                    "r": -98.288221
                },
                {
                    "index": 88,
                    "r": -1000.0
                },
                {
                    "index": 89,
                    "r": 1035.9845
                },
                {
                    "index": 90,
                    "r": -1003.4315
                },
                {
                    "index": 91,
                    "r": 1010.9665
                },
                {
                    "index": 92,
                    "r": 1026.6515
                },
                {
                    "index": 93,
                    "r": -1000.0
                },
                {
                    "index": 94,
                    "r": 203.113
                },
                {
                    "index": 95,
                    "r": -109.195196
                },
                {
                    "index": 96,
                    "r": 1010.832473
                },
                {
                    "index": 97,
                    "r": -107.981374
                },
                {
                    "index": 98,
                    "r": 1012.11006
                },
                {
                    "index": 99,
                    "r": -101.586728
                }
            ]
        },
        "mark": {
            "type": "line",
            "color": "#0088FF"
        },
        "encoding": {
            "x": {
                "field": "index",
                "type": "quantitative"
            },
            "y": {
                "field": "r",
                "type": "quantitative"
            }
        },
        "background": "transparent"
    },
    "logs": [
        {
            "t": 14,
            "r": -101.6,
            "l": 288,
            "beh": "📉 Loss Cut"
        },
        {
            "t": 13,
            "r": 1012.1,
            "l": 101,
            "beh": "🚀 BIG WIN"
        },
        {
            "t": 12,
            "r": -108.0,
            "l": 288,
            "beh": "📉 Loss Cut"
        },
        {
            "t": 11,
            "r": 1010.8,
            "l": 102,
            "beh": "🚀 BIG WIN"
        },
        {
            "t": 10,
            "r": -109.2,
            "l": 288,
            "beh": "📉 Loss Cut"
        },
        {
            "t": 9,
            "r": 203.1,
            "l": 288,
            "beh": "💵 Profit"
        },
        {
            "t": 8,
            "r": -1000.0,
            "l": 79,
            "beh": "💀 BUSTED"
        },
        {
            "t": 7,
            "r": 1026.7,
            "l": 113,
            "beh": "🚀 BIG WIN"
        },
        {
            "t": 6,
            "r": 1011.0,
            "l": 21,
            "beh": "🚀 BIG WIN"
        },
        {
            "t": 5,
            "r": -1003.4,
            "l": 181,
            "beh": "💀 BUSTED"
        },
        {
            "t": 4,
            "r": 1036.0,
            "l": 225,
            "beh": "🚀 BIG WIN"
        },
        {
            "t": 3,
            "r": -1000.0,
            "l": 77,
            "beh": "💀 BUSTED"
        },
        {
            "t": 2,
            "r": -98.3,
            "l": 288,
            "beh": "📉 Loss Cut"
        },
        {
            "t": 1,
            "r": -106.0,
            "l": 288,
            "beh": "📉 Loss Cut"
        },
        {
            "t": 0,
            "r": 1012.3,
            "l": 241,
            "beh": "🚀 BIG WIN"
        }
    ]
}