{
    "status": "active",
    "total_steps": 2275201,
    "target_steps": 3000000,
    "meters": {
        "pressure": {
            "val": 75.8,
            "color": "#238636"
        },
        "maturity": {
            "val": 100,
            "color": "#dbab09"
        }
    },
    "diagnosis": {
        "status_text": "生存の兆しあり (黄)",
        "status_color": "#d29922",
        "status_detail": "直近100戦: 49勝 (49%)"
    },
    "combat_stats": {
        "WIN": 16016,
        "FAIL": 945,
        "BUST": 10266
    },
    "ai_status": "Training (2,275,201)",
    "total_eps": 27227,
    "config": {
        "zones": [
            {
                "range": "0 - 33",
                "color": "#da3633",
                "title": "Zone 1: Awakening (赤)",
                "desc": "初期段階。勝率30%未満、または学習序盤。"
            },
            {
                "range": "33 - 66",
                "color": "#d29922",
                "title": "Zone 2: Hunting (橙)",
                "desc": "成長段階。勝率30-60%、または学習中盤。"
            },
            {
                "range": "66 - 99",
                "color": "#238636",
                "title": "Zone 3: Apex Predator (緑)",
                "desc": "完成段階。勝率60%以上、または学習終盤。"
            },
            {
                "range": "100",
                "color": "#dbab09",
                "title": "Zone 4: FANTASTIC BEAST (金)",
                "desc": "神の領域。勝率80%以上かつ完走。レインボー発動。"
            }
        ]
    },
    "analysis_report": {
        "overall_win_rate": "58.82 %",
        "overall_bust_rate": "37.71 %",
        "speed_stats": {
            "fastest": 2,
            "slowest": 288,
            "avg": 83.8
        },
        "margin_stats": {
            "lowest": 50.0,
            "highest": 999.0,
            "avg": 626.3
        },
        "distributions": {
            "speed": {
                "0-5m": 442,
                "5-30m": 6079,
                "30-60m": 3093,
                "60-120m": 2506,
                "120m+": 3896
            },
            "margin": {
                "50-60%": 44,
                "60-70%": 49,
                "70-80%": 51,
                "80-90%": 46,
                "90-100%": 62,
                "100%+": 15764
            }
        },
        "total_wins": 16016
    },
    "logs": [
        {
            "t": 14,
            "r": 9954.9,
            "l": 163,
            "beh": "WIN"
        },
        {
            "t": 13,
            "r": -23041.6,
            "l": 76,
            "beh": "DEATH"
        },
        {
            "t": 12,
            "r": -46030.7,
            "l": 55,
            "beh": "DEATH"
        },
        {
            "t": 11,
            "r": 10025.4,
            "l": 102,
            "beh": "WIN"
        },
        {
            "t": 10,
            "r": -33022.7,
            "l": 288,
            "beh": "DEATH"
        },
        {
            "t": 9,
            "r": 9947.1,
            "l": 288,
            "beh": "WIN"
        },
        {
            "t": 8,
            "r": -13003.5,
            "l": 288,
            "beh": "DEATH"
        },
        {
            "t": 7,
            "r": 10022.6,
            "l": 138,
            "beh": "WIN"
        },
        {
            "t": 6,
            "r": -10052.9,
            "l": 288,
            "beh": "DEATH"
        },
        {
            "t": 5,
            "r": -10052.9,
            "l": 288,
            "beh": "DEATH"
        },
        {
            "t": 4,
            "r": -23885.3,
            "l": 256,
            "beh": "DEATH"
        },
        {
            "t": 3,
            "r": -23022.0,
            "l": 111,
            "beh": "DEATH"
        },
        {
            "t": 2,
            "r": -23020.5,
            "l": 73,
            "beh": "DEATH"
        },
        {
            "t": 1,
            "r": -23019.2,
            "l": 10,
            "beh": "DEATH"
        },
        {
            "t": 0,
            "r": -12935.8,
            "l": 45,
            "beh": "DEATH"
        }
    ]
}