{
    "status": "active",
    "total_steps": 1085530,
    "target_steps": 3000000,
    "meters": {
        "pressure": {
            "val": 36.2,
            "color": "#d29922"
        },
        "maturity": {
            "val": 74,
            "color": "#238636"
        }
    },
    "diagnosis": {
        "status_text": "生存の兆しあり (黄)",
        "status_color": "#d29922",
        "status_detail": "直近100戦: 44勝 (44%)"
    },
    "combat_stats": {
        "WIN": 11220,
        "FAIL": 362,
        "BUST": 6987
    },
    "ai_status": "Training (1,085,530)",
    "total_eps": 18569,
    "config": {
        "zones": [
            {
                "range": "0 - 33",
                "color": "#da3633",
                "title": "Zone 1: Awakening (赤)",
                "desc": "初期段階。勝率30%未満、または学習序盤。"
            },
            {
                "range": "33 - 66",
                "color": "#d29922",
                "title": "Zone 2: Hunting (橙)",
                "desc": "成長段階。勝率30-60%、または学習中盤。"
            },
            {
                "range": "66 - 99",
                "color": "#238636",
                "title": "Zone 3: Apex Predator (緑)",
                "desc": "完成段階。勝率60%以上、または学習終盤。"
            },
            {
                "range": "100",
                "color": "#dbab09",
                "title": "Zone 4: FANTASTIC BEAST (金)",
                "desc": "神の領域。勝率80%以上かつ完走。レインボー発動。"
            }
        ]
    },
    "analysis_report": {
        "overall_win_rate": "60.42 %",
        "overall_bust_rate": "37.63 %",
        "speed_stats": {
            "fastest": 2,
            "slowest": 288,
            "avg": 55.3
        },
        "margin_stats": {
            "lowest": 50.0,
            "highest": 999.0,
            "avg": 640.2
        },
        "distributions": {
            "speed": {
                "0-5m": 431,
                "5-30m": 5580,
                "30-60m": 2385,
                "60-120m": 1465,
                "120m+": 1359
            },
            "margin": {
                "50-60%": 28,
                "60-70%": 29,
                "70-80%": 33,
                "80-90%": 34,
                "90-100%": 39,
                "100%+": 11057
            }
        },
        "total_wins": 11220
    },
    "logs": [
        {
            "t": 14,
            "r": -1606.2,
            "l": 99,
            "beh": "FAIL"
        },
        {
            "t": 13,
            "r": -2564.8,
            "l": 128,
            "beh": "FAIL"
        },
        {
            "t": 12,
            "r": -23013.4,
            "l": 107,
            "beh": "DEATH"
        },
        {
            "t": 11,
            "r": -11540.0,
            "l": 16,
            "beh": "DEATH"
        },
        {
            "t": 10,
            "r": 9985.2,
            "l": 27,
            "beh": "WIN"
        },
        {
            "t": 9,
            "r": -23029.1,
            "l": 109,
            "beh": "DEATH"
        },
        {
            "t": 8,
            "r": -23027.5,
            "l": 93,
            "beh": "DEATH"
        },
        {
            "t": 7,
            "r": 9979.5,
            "l": 12,
            "beh": "WIN"
        },
        {
            "t": 6,
            "r": 10313.5,
            "l": 106,
            "beh": "WIN"
        },
        {
            "t": 5,
            "r": 10010.4,
            "l": 41,
            "beh": "WIN"
        },
        {
            "t": 4,
            "r": 9985.7,
            "l": 56,
            "beh": "WIN"
        },
        {
            "t": 3,
            "r": -47557.6,
            "l": 14,
            "beh": "DEATH"
        },
        {
            "t": 2,
            "r": -23875.9,
            "l": 43,
            "beh": "DEATH"
        },
        {
            "t": 1,
            "r": 9594.8,
            "l": 75,
            "beh": "WIN"
        },
        {
            "t": 0,
            "r": 9970.8,
            "l": 78,
            "beh": "WIN"
        }
    ]
}