{
    "status": "active",
    "total_steps": 261139,
    "target_steps": 3000000,
    "prog_pct": 8.7,
    "phase_title": "Phase 1: Awakening (野性の目覚め)",
    "phase_desc": "初期段階。まずは相場の脈動を感じ取る時期。",
    "phase_color": "#da3633",
    "maturity": {
        "title": "Phase 2: Hunting (狩りの学習)",
        "color": "#d29922",
        "id": 2
    },
    "diagnosis": {
        "status_text": "生存の兆しあり (黄)",
        "status_color": "#d29922",
        "status_detail": "直近100戦: 57勝 / 勝率 57%",
        "sniper_stats": {
            "mission_rate": "62.9 %",
            "speed_range": "2 - 288",
            "margin_range": "52.0 - 999.0 %"
        }
    },
    "combat_stats": {
        "WIN": 2415,
        "FAIL": 67,
        "BUST": 1355
    },
    "ai_status": "Training (261,139)",
    "total_eps": 3837,
    "avg_score": 0,
    "config": {
        "phases": [
            {
                "id": 1,
                "min_pct": 0,
                "max_pct": 33,
                "color": "#da3633",
                "title": "Phase 1: Awakening (野性の目覚め)",
                "goal": "初期段階。まずは相場の脈動を感じ取る時期。"
            },
            {
                "id": 2,
                "min_pct": 33,
                "max_pct": 66,
                "color": "#d29922",
                "title": "Phase 2: Hunting (狩りの学習)",
                "goal": "成長段階。無駄撃ちを減らし、勝てる時だけ撃つ時期。"
            },
            {
                "id": 3,
                "min_pct": 66,
                "max_pct": 100,
                "color": "#238636",
                "title": "Phase 3: Apex Predator (頂点捕食者)",
                "goal": "完成間近。即死ペナルティの中で精度を極める時期。"
            },
            {
                "id": 4,
                "min_pct": 100,
                "max_pct": 9999,
                "color": "#dbab09",
                "title": "Phase 4: FANTASTIC BEAST",
                "goal": "神の領域。全てを超越した存在。"
            }
        ]
    },
    "logs": [
        {
            "t": 14,
            "r": 9660.4,
            "l": 258,
            "beh": "WIN"
        },
        {
            "t": 13,
            "r": 9940.3,
            "l": 180,
            "beh": "WIN"
        },
        {
            "t": 12,
            "r": 8796.1,
            "l": 211,
            "beh": "WIN"
        },
        {
            "t": 11,
            "r": 8686.5,
            "l": 75,
            "beh": "WIN"
        },
        {
            "t": 10,
            "r": 6316.2,
            "l": 169,
            "beh": "WIN"
        },
        {
            "t": 9,
            "r": 10029.9,
            "l": 205,
            "beh": "WIN"
        },
        {
            "t": 8,
            "r": 10113.5,
            "l": 73,
            "beh": "WIN"
        },
        {
            "t": 7,
            "r": 9999.5,
            "l": 107,
            "beh": "WIN"
        },
        {
            "t": 6,
            "r": 9936.0,
            "l": 194,
            "beh": "WIN"
        },
        {
            "t": 5,
            "r": 10038.4,
            "l": 134,
            "beh": "WIN"
        },
        {
            "t": 4,
            "r": 8129.6,
            "l": 274,
            "beh": "WIN"
        },
        {
            "t": 3,
            "r": 2959.2,
            "l": 288,
            "beh": "CUT/WAIT"
        },
        {
            "t": 2,
            "r": 9976.1,
            "l": 108,
            "beh": "WIN"
        },
        {
            "t": 1,
            "r": 9974.9,
            "l": 22,
            "beh": "WIN"
        },
        {
            "t": 0,
            "r": 9258.1,
            "l": 80,
            "beh": "WIN"
        }
    ]
}