{
    "status": "active",
    "total_steps": 1517761,
    "target_steps": 3000000,
    "meters": {
        "pressure": {
            "val": 50.6,
            "color": "#d29922"
        },
        "maturity": {
            "val": 90,
            "color": "#238636"
        }
    },
    "diagnosis": {
        "status_text": "生存の兆しあり (黄)",
        "status_color": "#d29922",
        "status_detail": "直近100戦: 49勝 (49%)"
    },
    "combat_stats": {
        "WIN": 13542,
        "FAIL": 516,
        "BUST": 8496
    },
    "ai_status": "Training (1,517,761)",
    "total_eps": 22554,
    "config": {
        "zones": [
            {
                "range": "0 - 33",
                "color": "#da3633",
                "title": "Zone 1: Awakening (赤)",
                "desc": "初期段階。勝率30%未満、または学習序盤。"
            },
            {
                "range": "33 - 66",
                "color": "#d29922",
                "title": "Zone 2: Hunting (橙)",
                "desc": "成長段階。勝率30-60%、または学習中盤。"
            },
            {
                "range": "66 - 99",
                "color": "#238636",
                "title": "Zone 3: Apex Predator (緑)",
                "desc": "完成段階。勝率60%以上、または学習終盤。"
            },
            {
                "range": "100",
                "color": "#dbab09",
                "title": "Zone 4: FANTASTIC BEAST (金)",
                "desc": "神の領域。勝率80%以上かつ完走。レインボー発動。"
            }
        ]
    },
    "analysis_report": {
        "overall_win_rate": "60.04 %",
        "overall_bust_rate": "37.67 %",
        "speed_stats": {
            "fastest": 2,
            "slowest": 288,
            "avg": 65.6
        },
        "margin_stats": {
            "lowest": 50.0,
            "highest": 999.0,
            "avg": 634.0
        },
        "distributions": {
            "speed": {
                "0-5m": 439,
                "5-30m": 5979,
                "30-60m": 2871,
                "60-120m": 2033,
                "120m+": 2220
            },
            "margin": {
                "50-60%": 37,
                "60-70%": 36,
                "70-80%": 41,
                "80-90%": 39,
                "90-100%": 49,
                "100%+": 13340
            }
        },
        "total_wins": 13542
    },
    "logs": [
        {
            "t": 14,
            "r": 9947.1,
            "l": 288,
            "beh": "WIN"
        },
        {
            "t": 13,
            "r": -31388.5,
            "l": 270,
            "beh": "DEATH"
        },
        {
            "t": 12,
            "r": 9957.2,
            "l": 288,
            "beh": "WIN"
        },
        {
            "t": 11,
            "r": 9947.1,
            "l": 288,
            "beh": "WIN"
        },
        {
            "t": 10,
            "r": -15710.1,
            "l": 38,
            "beh": "DEATH"
        },
        {
            "t": 9,
            "r": 9981.3,
            "l": 71,
            "beh": "WIN"
        },
        {
            "t": 8,
            "r": 9998.3,
            "l": 99,
            "beh": "WIN"
        },
        {
            "t": 7,
            "r": -15708.2,
            "l": 49,
            "beh": "DEATH"
        },
        {
            "t": 6,
            "r": -26136.8,
            "l": 288,
            "beh": "DEATH"
        },
        {
            "t": 5,
            "r": -15705.2,
            "l": 78,
            "beh": "DEATH"
        },
        {
            "t": 4,
            "r": -15702.7,
            "l": 196,
            "beh": "DEATH"
        },
        {
            "t": 3,
            "r": 10003.4,
            "l": 67,
            "beh": "WIN"
        },
        {
            "t": 2,
            "r": -5701.3,
            "l": 288,
            "beh": "FAIL"
        },
        {
            "t": 1,
            "r": -15699.9,
            "l": 155,
            "beh": "DEATH"
        },
        {
            "t": 0,
            "r": -32320.6,
            "l": 273,
            "beh": "DEATH"
        }
    ]
}