{
    "status": "active",
    "total_steps": 380737,
    "target_steps": 3000000,
    "meters": {
        "pressure": {
            "val": 12.7,
            "color": "#da3633"
        },
        "maturity": {
            "val": 42,
            "color": "#d29922"
        }
    },
    "diagnosis": {
        "status_text": "生存の兆しあり (黄)",
        "status_color": "#d29922",
        "status_detail": "直近100戦: 52勝 (52%)"
    },
    "combat_stats": {
        "WIN": 6337,
        "FAIL": 69,
        "BUST": 3725
    },
    "ai_status": "Training (380,737)",
    "total_eps": 10131,
    "config": {
        "zones": [
            {
                "range": "0 - 33",
                "color": "#da3633",
                "title": "Zone 1: Awakening (赤)",
                "desc": "初期段階。勝率30%未満、または学習序盤。"
            },
            {
                "range": "33 - 66",
                "color": "#d29922",
                "title": "Zone 2: Hunting (橙)",
                "desc": "成長段階。勝率30-60%、または学習中盤。"
            },
            {
                "range": "66 - 99",
                "color": "#238636",
                "title": "Zone 3: Apex Predator (緑)",
                "desc": "完成段階。勝率60%以上、または学習終盤。"
            },
            {
                "range": "100",
                "color": "#dbab09",
                "title": "Zone 4: FANTASTIC BEAST (金)",
                "desc": "神の領域。勝率80%以上かつ完走。レインボー発動。"
            }
        ]
    },
    "analysis_report": {
        "overall_win_rate": "62.55 %",
        "overall_bust_rate": "36.77 %",
        "speed_stats": {
            "fastest": 2,
            "slowest": 288,
            "avg": 34.0
        },
        "margin_stats": {
            "lowest": 50.0,
            "highest": 999.0,
            "avg": 651.7
        },
        "distributions": {
            "speed": {
                "0-5m": 338,
                "5-30m": 3919,
                "30-60m": 1264,
                "60-120m": 546,
                "120m+": 270
            },
            "margin": {
                "50-60%": 12,
                "60-70%": 15,
                "70-80%": 17,
                "80-90%": 19,
                "90-100%": 18,
                "100%+": 6256
            }
        },
        "total_wins": 6337
    },
    "logs": [
        {
            "t": 14,
            "r": 10000.7,
            "l": 72,
            "beh": "WIN"
        },
        {
            "t": 13,
            "r": 3994.3,
            "l": 286,
            "beh": "WAIT"
        },
        {
            "t": 12,
            "r": -15651.4,
            "l": 288,
            "beh": "DEATH"
        },
        {
            "t": 11,
            "r": -4725.2,
            "l": 153,
            "beh": "FAIL"
        },
        {
            "t": 10,
            "r": -4722.8,
            "l": 57,
            "beh": "FAIL"
        },
        {
            "t": 9,
            "r": 8113.6,
            "l": 51,
            "beh": "WIN"
        },
        {
            "t": 8,
            "r": -10093.9,
            "l": 114,
            "beh": "DEATH"
        },
        {
            "t": 7,
            "r": -18057.8,
            "l": 288,
            "beh": "DEATH"
        },
        {
            "t": 6,
            "r": -9376.6,
            "l": 26,
            "beh": "FAIL"
        },
        {
            "t": 5,
            "r": -4715.7,
            "l": 87,
            "beh": "FAIL"
        },
        {
            "t": 4,
            "r": 9870.5,
            "l": 8,
            "beh": "WIN"
        },
        {
            "t": 3,
            "r": 9996.2,
            "l": 56,
            "beh": "WIN"
        },
        {
            "t": 2,
            "r": -9381.4,
            "l": 64,
            "beh": "FAIL"
        },
        {
            "t": 1,
            "r": 9985.6,
            "l": 20,
            "beh": "WIN"
        },
        {
            "t": 0,
            "r": 9874.3,
            "l": 8,
            "beh": "WIN"
        }
    ]
}