{
    "status": "active",
    "total_steps": 1780736,
    "target_steps": 2000000,
    "prog_pct": 89.0,
    "diagnosis": {
        "expected_phase": "Phase 4: 覇道",
        "actual_phase": "Phase 2: 血塗れの学習",
        "status_text": "⚠️ 成長停滞 (NEET WARNING)",
        "status_color": "#FF4B4B"
    },
    "ai_status": "Learning (1,780,736 / 2,000,000)",
    "total_eps": 100,
    "avg_score": -143.0,
    "surv_rate": 55.0,
    "bust_rate": 34.0,
    "config": {
        "phases": [
            {
                "id": 1,
                "limit_ratio": 0.2,
                "color": "#FF4B4B",
                "min_score": -9999,
                "title": "Phase 1: 阿鼻叫喚の特攻",
                "desc": "資金管理を学習中（暴走・即死）"
            },
            {
                "id": 2,
                "limit_ratio": 0.5,
                "color": "#FFA500",
                "min_score": -500,
                "title": "Phase 2: 血塗れの学習",
                "desc": "生存時間の延長・逃げ腰"
            },
            {
                "id": 3,
                "limit_ratio": 0.7,
                "color": "#FFFF00",
                "min_score": -100,
                "title": "Phase 3: 覚醒への分水嶺",
                "desc": "損小利大の萌芽・生存確立"
            },
            {
                "id": 4,
                "limit_ratio": 0.9,
                "color": "#00FF00",
                "min_score": 100,
                "title": "Phase 4: 覇道",
                "desc": "トレンドフォロー・利益追求"
            },
            {
                "id": 5,
                "limit_ratio": 1.01,
                "color": "#0088FF",
                "min_score": 500,
                "title": "Phase 5: 市場支配",
                "desc": "完成されたロジック"
            }
        ]
    },
    "chart_json": {
        "$schema": "https://vega.github.io/schema/vega-lite/v5.json",
        "data": {
            "values": [
                {
                    "Type": "即死・破綻",
                    "Count": 34,
                    "Color": "#FF4B4B"
                },
                {
                    "Type": "損切り・敗北",
                    "Count": 32,
                    "Color": "#FFA500"
                },
                {
                    "Type": "辛勝・微益",
                    "Count": 10,
                    "Color": "#FFFF00"
                },
                {
                    "Type": "大勝利",
                    "Count": 24,
                    "Color": "#00FF00"
                }
            ]
        },
        "layer": [
            {
                "mark": "bar",
                "encoding": {
                    "x": {
                        "field": "Count",
                        "type": "quantitative",
                        "axis": {
                            "labelColor": "#ddd"
                        }
                    },
                    "y": {
                        "field": "Type",
                        "type": "nominal",
                        "sort": [
                            "大勝利",
                            "辛勝・微益",
                            "損切り・敗北",
                            "即死・破綻"
                        ],
                        "axis": {
                            "labelColor": "#ddd"
                        }
                    },
                    "color": {
                        "field": "Color",
                        "scale": null
                    }
                }
            },
            {
                "mark": {
                    "type": "text",
                    "align": "left",
                    "dx": 5,
                    "fill": "white"
                },
                "encoding": {
                    "x": {
                        "field": "Count",
                        "type": "quantitative"
                    },
                    "y": {
                        "field": "Type",
                        "type": "nominal"
                    },
                    "text": {
                        "field": "Count",
                        "type": "quantitative"
                    }
                }
            }
        ],
        "background": "transparent"
    },
    "line_json": {
        "$schema": "https://vega.github.io/schema/vega-lite/v5.json",
        "data": {
            "values": [
                {
                    "index": 0,
                    "r": -104.960631
                },
                {
                    "index": 1,
                    "r": -1009.297314
                },
                {
                    "index": 2,
                    "r": -1007.207398
                },
                {
                    "index": 3,
                    "r": -1009.2315
                },
                {
                    "index": 4,
                    "r": -1005.049799
                },
                {
                    "index": 5,
                    "r": 97.571657
                },
                {
                    "index": 6,
                    "r": 197.248969
                },
                {
                    "index": 7,
                    "r": -96.268244
                },
                {
                    "index": 8,
                    "r": 1010.404
                },
                {
                    "index": 9,
                    "r": -109.208219
                },
                {
                    "index": 10,
                    "r": -998.481732
                },
                {
                    "index": 11,
                    "r": -108.885756
                },
                {
                    "index": 12,
                    "r": -104.504473
                },
                {
                    "index": 13,
                    "r": 1016.826656
                },
                {
                    "index": 14,
                    "r": -993.896
                },
                {
                    "index": 15,
                    "r": -1003.68499
                },
                {
                    "index": 16,
                    "r": -107.599009
                },
                {
                    "index": 17,
                    "r": 1017.956369
                },
                {
                    "index": 18,
                    "r": -109.532792
                },
                {
                    "index": 19,
                    "r": 1011.5265
                },
                {
                    "index": 20,
                    "r": 1013.106244
                },
                {
                    "index": 21,
                    "r": -1001.243583
                },
                {
                    "index": 22,
                    "r": -1004.582538
                },
                {
                    "index": 23,
                    "r": -993.794414
                },
                {
                    "index": 24,
                    "r": -107.657802
                },
                {
                    "index": 25,
                    "r": -1003.7235
                },
                {
                    "index": 26,
                    "r": -105.511883
                },
                {
                    "index": 27,
                    "r": 1009.687662
                },
                {
                    "index": 28,
                    "r": 97.389699
                },
                {
                    "index": 29,
                    "r": 1012.796
                },
                {
                    "index": 30,
                    "r": 1011.9775
                },
                {
                    "index": 31,
                    "r": -1001.5545
                },
                {
                    "index": 32,
                    "r": 102.812505
                },
                {
                    "index": 33,
                    "r": -1003.235439
                },
                {
                    "index": 34,
                    "r": 203.332947
                },
                {
                    "index": 35,
                    "r": -106.392717
                },
                {
                    "index": 36,
                    "r": -104.147561
                },
                {
                    "index": 37,
                    "r": 1026.930336
                },
                {
                    "index": 38,
                    "r": -105.27766
                },
                {
                    "index": 39,
                    "r": 1014.210458
                },
                {
                    "index": 40,
                    "r": 1010.0475
                },
                {
                    "index": 41,
                    "r": 99.439161
                },
                {
                    "index": 42,
                    "r": -109.738405
                },
                {
                    "index": 43,
                    "r": -105.271366
                },
                {
                    "index": 44,
                    "r": -1000.0
                },
                {
                    "index": 45,
                    "r": -111.627346
                },
                {
                    "index": 46,
                    "r": -998.2405
                },
                {
                    "index": 47,
                    "r": 1014.32961
                },
                {
                    "index": 48,
                    "r": 96.397767
                },
                {
                    "index": 49,
                    "r": -1000.0
                },
                {
                    "index": 50,
                    "r": -1010.105896
                },
                {
                    "index": 51,
                    "r": 1008.729436
                },
                {
                    "index": 52,
                    "r": -108.940743
                },
                {
                    "index": 53,
                    "r": -1007.107594
                },
                {
                    "index": 54,
                    "r": -104.989764
                },
                {
                    "index": 55,
                    "r": -96.172212
                },
                {
                    "index": 56,
                    "r": 200.181633
                },
                {
                    "index": 57,
                    "r": -1000.25251
                },
                {
                    "index": 58,
                    "r": 1009.227986
                },
                {
                    "index": 59,
                    "r": 1009.526
                },
                {
                    "index": 60,
                    "r": -1000.923949
                },
                {
                    "index": 61,
                    "r": -1000.0
                },
                {
                    "index": 62,
                    "r": 1010.894953
                },
                {
                    "index": 63,
                    "r": -1012.37602
                },
                {
                    "index": 64,
                    "r": 1014.912893
                },
                {
                    "index": 65,
                    "r": 205.601493
                },
                {
                    "index": 66,
                    "r": 1011.198158
                },
                {
                    "index": 67,
                    "r": -109.390786
                },
                {
                    "index": 68,
                    "r": -1008.492945
                },
                {
                    "index": 69,
                    "r": -108.28297
                },
                {
                    "index": 70,
                    "r": -107.942397
                },
                {
                    "index": 71,
                    "r": -996.476432
                },
                {
                    "index": 72,
                    "r": -1006.550606
                },
                {
                    "index": 73,
                    "r": -104.887979
                },
                {
                    "index": 74,
                    "r": 204.089242
                },
                {
                    "index": 75,
                    "r": 1012.876595
                },
                {
                    "index": 76,
                    "r": 1013.311796
                },
                {
                    "index": 77,
                    "r": -1012.089638
                },
                {
                    "index": 78,
                    "r": -991.759791
                },
                {
                    "index": 79,
                    "r": -107.166518
                },
                {
                    "index": 80,
                    "r": -1000.579395
                },
                {
                    "index": 81,
                    "r": -1009.828409
                },
                {
                    "index": 82,
                    "r": -1001.552174
                },
                {
                    "index": 83,
                    "r": -1009.497947
                },
                {
                    "index": 84,
                    "r": -104.91621
                },
                {
                    "index": 85,
                    "r": -1000.0
                },
                {
                    "index": 86,
                    "r": 1013.569981
                },
                {
                    "index": 87,
                    "r": -105.637568
                },
                {
                    "index": 88,
                    "r": -1009.699298
                },
                {
                    "index": 89,
                    "r": -1012.504345
                },
                {
                    "index": 90,
                    "r": -108.371449
                },
                {
                    "index": 91,
                    "r": -110.977202
                },
                {
                    "index": 92,
                    "r": 1012.658056
                },
                {
                    "index": 93,
                    "r": -114.221412
                },
                {
                    "index": 94,
                    "r": -108.739013
                },
                {
                    "index": 95,
                    "r": -108.968986
                },
                {
                    "index": 96,
                    "r": -108.828263
                },
                {
                    "index": 97,
                    "r": 1022.41599
                },
                {
                    "index": 98,
                    "r": -102.143577
                },
                {
                    "index": 99,
                    "r": 1012.051331
                }
            ]
        },
        "mark": {
            "type": "line",
            "color": "#0088FF"
        },
        "encoding": {
            "x": {
                "field": "index",
                "type": "quantitative"
            },
            "y": {
                "field": "r",
                "type": "quantitative"
            }
        },
        "background": "transparent"
    },
    "logs": [
        {
            "t": 14,
            "r": 1012.1,
            "l": 62,
            "beh": "🚀 BIG WIN"
        },
        {
            "t": 13,
            "r": -102.1,
            "l": 288,
            "beh": "📉 Loss Cut"
        },
        {
            "t": 12,
            "r": 1022.4,
            "l": 174,
            "beh": "🚀 BIG WIN"
        },
        {
            "t": 11,
            "r": -108.8,
            "l": 288,
            "beh": "📉 Loss Cut"
        },
        {
            "t": 10,
            "r": -109.0,
            "l": 288,
            "beh": "📉 Loss Cut"
        },
        {
            "t": 9,
            "r": -108.7,
            "l": 288,
            "beh": "📉 Loss Cut"
        },
        {
            "t": 8,
            "r": -114.2,
            "l": 288,
            "beh": "📉 Loss Cut"
        },
        {
            "t": 7,
            "r": 1012.7,
            "l": 201,
            "beh": "🚀 BIG WIN"
        },
        {
            "t": 6,
            "r": -111.0,
            "l": 288,
            "beh": "📉 Loss Cut"
        },
        {
            "t": 5,
            "r": -108.4,
            "l": 288,
            "beh": "📉 Loss Cut"
        },
        {
            "t": 4,
            "r": -1012.5,
            "l": 253,
            "beh": "💀 BUSTED"
        },
        {
            "t": 3,
            "r": -1009.7,
            "l": 75,
            "beh": "💀 BUSTED"
        },
        {
            "t": 2,
            "r": -105.6,
            "l": 288,
            "beh": "📉 Loss Cut"
        },
        {
            "t": 1,
            "r": 1013.6,
            "l": 26,
            "beh": "🚀 BIG WIN"
        },
        {
            "t": 0,
            "r": -1000.0,
            "l": 8,
            "beh": "💀 BUSTED"
        }
    ]
}